<?xml version="1.0" encoding="UTF-8" ?>
<XMLDB PATH="mod/pdfannotator/db" VERSION="20221101" COMMENT="XMLDB file for Moodle mod/pdfannotator"
    xmlns:xsi="http://www.w3.org/2001/XMLSchema-instance"
    xsi:noNamespaceSchemaLocation="../../../lib/xmldb/xmldb.xsd"
>
  <TABLES>
    <TABLE NAME="pdfannotator" COMMENT="Defines pdfannotator">
      <FIELDS>
        <FIELD NAME="id" TYPE="int" LENGTH="10" NOTNULL="true" SEQUENCE="true"/>
        <FIELD NAME="course" TYPE="int" LENGTH="10" NOTNULL="true" DEFAULT="0" SEQUENCE="false"/>
        <FIELD NAME="name" TYPE="char" LENGTH="255" NOTNULL="true" SEQUENCE="false"/>
        <FIELD NAME="intro" TYPE="text" NOTNULL="false" SEQUENCE="false"/>
        <FIELD NAME="introformat" TYPE="int" LENGTH="4" NOTNULL="true" DEFAULT="0" SEQUENCE="false"/>
        <FIELD NAME="usevotes" TYPE="int" LENGTH="4" NOTNULL="true" DEFAULT="1" SEQUENCE="false"/>
        <FIELD NAME="useprint" TYPE="int" LENGTH="4" NOTNULL="true" DEFAULT="0" SEQUENCE="false"/>
        <FIELD NAME="useprintcomments" TYPE="int" LENGTH="2" NOTNULL="true" DEFAULT="0" SEQUENCE="false" COMMENT="Allow participants to print comments"/>
        <FIELD NAME="use_studenttextbox" TYPE="int" LENGTH="2" NOTNULL="true" DEFAULT="0" SEQUENCE="false"/>
        <FIELD NAME="use_studentdrawing" TYPE="int" LENGTH="2" NOTNULL="true" DEFAULT="0" SEQUENCE="false"/>
        <FIELD NAME="useprivatecomments" TYPE="int" LENGTH="2" NOTNULL="true" DEFAULT="0" SEQUENCE="false"/>
        <FIELD NAME="useprotectedcomments" TYPE="int" LENGTH="2" NOTNULL="true" DEFAULT="0" SEQUENCE="false"/>
        <FIELD NAME="timecreated" TYPE="int" LENGTH="10" NOTNULL="true" DEFAULT="0" SEQUENCE="false"/>
        <FIELD NAME="timemodified" TYPE="int" LENGTH="10" NOTNULL="true" DEFAULT="0" SEQUENCE="false"/>
      </FIELDS>
      <KEYS>
        <KEY NAME="primary" TYPE="primary" FIELDS="id" COMMENT="Primary key for pdfannotator"/>
      </KEYS>
    </TABLE>
    <TABLE NAME="pdfannotator_default_setting" COMMENT="Default settings for pdfannotator">
      <FIELDS>
        <FIELD NAME="id" TYPE="int" LENGTH="10" NOTNULL="true" SEQUENCE="true"/>
        <FIELD NAME="allowanonymous" TYPE="binary" NOTNULL="false" SEQUENCE="false" COMMENT="allowing anonymous posting"/>
      </FIELDS>
      <KEYS>
        <KEY NAME="primary" TYPE="primary" FIELDS="id"/>
      </KEYS>
    </TABLE>
    <TABLE NAME="pdfannotator_comments" COMMENT="Saves the comments to each annotation">
      <FIELDS>
        <FIELD NAME="id" TYPE="int" LENGTH="10" NOTNULL="true" SEQUENCE="true"/>
        <FIELD NAME="pdfannotatorid" TYPE="int" LENGTH="10" NOTNULL="true" DEFAULT="-1" SEQUENCE="false"/>
        <FIELD NAME="annotationid" TYPE="int" LENGTH="10" NOTNULL="true" SEQUENCE="false"/>
        <FIELD NAME="userid" TYPE="int" LENGTH="10" NOTNULL="true" SEQUENCE="false"/>
        <FIELD NAME="content" TYPE="text" NOTNULL="false" SEQUENCE="false"/>
        <FIELD NAME="timecreated" TYPE="int" LENGTH="11" NOTNULL="true" SEQUENCE="false"/>
        <FIELD NAME="timemodified" TYPE="int" LENGTH="11" NOTNULL="true" SEQUENCE="false" COMMENT="This is a timestamp, which should be altered, if the dataset is modified."/>
        <FIELD NAME="modifiedby" TYPE="int" LENGTH="10" NOTNULL="false" SEQUENCE="false"/>
        <FIELD NAME="visibility" TYPE="char" LENGTH="45" NOTNULL="true" DEFAULT="public" SEQUENCE="false"/>
        <FIELD NAME="isquestion" TYPE="int" LENGTH="2" NOTNULL="true" DEFAULT="0" SEQUENCE="false" COMMENT="When the user creates an annotation, the comment he has to write is a question. So this column has to be true, otherwise false."/>
        <FIELD NAME="isdeleted" TYPE="int" LENGTH="2" NOTNULL="true" DEFAULT="0" SEQUENCE="false"/>
        <FIELD NAME="ishidden" TYPE="int" LENGTH="2" NOTNULL="false" DEFAULT="0" SEQUENCE="false" COMMENT="Hidden comments can be seen by managers but not participants."/>
        <FIELD NAME="solved" TYPE="int" LENGTH="10" NOTNULL="true" DEFAULT="0" SEQUENCE="false" COMMENT="saves the userid of the user who marked the comment question: marked as solved answer: marked as correct answer"/>
      </FIELDS>
      <KEYS>
        <KEY NAME="primary" TYPE="primary" FIELDS="id"/>
        <KEY NAME="annotationid" TYPE="foreign" FIELDS="annotationid" REFTABLE="annotations" REFFIELDS="id" COMMENT="Foreign Key for annotationid to annotations table"/>
        <KEY NAME="pdfannotatorid" TYPE="foreign" FIELDS="pdfannotatorid" REFTABLE="pdfannotator" REFFIELDS="id"/>
      </KEYS>
      <INDEXES>
        <INDEX NAME="userid" UNIQUE="false" FIELDS="userid" COMMENT="Index for userid"/>
      </INDEXES>
    </TABLE>
    <TABLE NAME="pdfannotator_reports" COMMENT="Saves reports concering comments">
      <FIELDS>
        <FIELD NAME="id" TYPE="int" LENGTH="10" NOTNULL="true" SEQUENCE="true"/>
        <FIELD NAME="commentid" TYPE="int" LENGTH="10" NOTNULL="true" SEQUENCE="false" COMMENT="This is the id of the comment, which is reported by this report"/>
        <FIELD NAME="courseid" TYPE="int" LENGTH="10" NOTNULL="true" SEQUENCE="false" COMMENT="This is the courseid of the corresponding course"/>
        <FIELD NAME="pdfannotatorid" TYPE="int" LENGTH="10" NOTNULL="true" SEQUENCE="false" COMMENT="This is the id of the corresponding pdfannotator instance"/>
        <FIELD NAME="message" TYPE="text" NOTNULL="false" SEQUENCE="false" COMMENT="message of the report, why the annotation is reported"/>
        <FIELD NAME="userid" TYPE="int" LENGTH="10" NOTNULL="true" SEQUENCE="false" COMMENT="This is the id of the user, who wrote the report"/>
        <FIELD NAME="timecreated" TYPE="int" LENGTH="10" NOTNULL="true" SEQUENCE="false"/>
        <FIELD NAME="seen" TYPE="int" LENGTH="2" NOTNULL="true" DEFAULT="0" SEQUENCE="false"/>
      </FIELDS>
      <KEYS>
        <KEY NAME="primary" TYPE="primary" FIELDS="id"/>
        <KEY NAME="commentid" TYPE="foreign" FIELDS="commentid" REFTABLE="comments" REFFIELDS="id" COMMENT="Foreignkey commentid for comments table"/>
      </KEYS>
    </TABLE>
    <TABLE NAME="pdfannotator_annotations" COMMENT="This table saves all the annotations of all the pdfannotator instances in this Moodle.">
      <FIELDS>
        <FIELD NAME="id" TYPE="int" LENGTH="10" NOTNULL="true" SEQUENCE="true"/>
        <FIELD NAME="pdfannotatorid" TYPE="int" LENGTH="10" NOTNULL="true" SEQUENCE="false"/>
        <FIELD NAME="page" TYPE="int" LENGTH="10" NOTNULL="true" SEQUENCE="false"/>
        <FIELD NAME="userid" TYPE="int" LENGTH="10" NOTNULL="true" DEFAULT="1" SEQUENCE="false"/>
        <FIELD NAME="annotationtypeid" TYPE="int" LENGTH="10" NOTNULL="true" SEQUENCE="false"/>
        <FIELD NAME="data" TYPE="text" NOTNULL="true" SEQUENCE="false"/>
        <FIELD NAME="timecreated" TYPE="int" LENGTH="10" NOTNULL="true" SEQUENCE="false"/>
        <FIELD NAME="timemodified" TYPE="int" LENGTH="10" NOTNULL="false" SEQUENCE="false"/>
        <FIELD NAME="modifiedby" TYPE="int" LENGTH="10" NOTNULL="false" SEQUENCE="false"/>
      </FIELDS>
      <KEYS>
        <KEY NAME="primary" TYPE="primary" FIELDS="id"/>
        <KEY NAME="pdfannotatorid" TYPE="foreign" FIELDS="pdfannotatorid" REFTABLE="pdfannotator" REFFIELDS="id"/>
        <KEY NAME="annotationtypeid" TYPE="foreign" FIELDS="annotationtypeid" REFTABLE="pdfannotator_annotationtypes" REFFIELDS="id"/>
      </KEYS>
    </TABLE>
    <TABLE NAME="pdfannotator_annotationtypes" COMMENT="This table allots an id to each annotationtype.">
      <FIELDS>
        <FIELD NAME="id" TYPE="int" LENGTH="10" NOTNULL="true" SEQUENCE="true"/>
        <FIELD NAME="name" TYPE="char" LENGTH="50" NOTNULL="true" SEQUENCE="false"/>
      </FIELDS>
      <KEYS>
        <KEY NAME="primary" TYPE="primary" FIELDS="id"/>
      </KEYS>
    </TABLE>
    <TABLE NAME="pdfannotator_votes" COMMENT="Saves the up-(and down)votes">
      <FIELDS>
        <FIELD NAME="id" TYPE="int" LENGTH="10" NOTNULL="true" SEQUENCE="true"/>
        <FIELD NAME="commentid" TYPE="int" LENGTH="10" NOTNULL="true" SEQUENCE="false"/>
        <FIELD NAME="userid" TYPE="int" LENGTH="10" NOTNULL="true" SEQUENCE="false"/>
        <FIELD NAME="vote" TYPE="int" LENGTH="4" NOTNULL="true" DEFAULT="1" SEQUENCE="false"/>
      </FIELDS>
      <KEYS>
        <KEY NAME="primary" TYPE="primary" FIELDS="id"/>
        <KEY NAME="commentid" TYPE="foreign" FIELDS="commentid" REFTABLE="comments" REFFIELDS="id" COMMENT="The foreign key of the comment table"/>
      </KEYS>
      <INDEXES>
        <INDEX NAME="userid" UNIQUE="false" FIELDS="userid" COMMENT="An index for userid."/>
      </INDEXES>
    </TABLE>
    <TABLE NAME="pdfannotator_subscriptions" COMMENT="saves which users subscribed to which questions">
      <FIELDS>
        <FIELD NAME="id" TYPE="int" LENGTH="10" NOTNULL="true" SEQUENCE="true"/>
        <FIELD NAME="userid" TYPE="int" LENGTH="10" NOTNULL="true" SEQUENCE="false"/>
        <FIELD NAME="annotationid" TYPE="int" LENGTH="10" NOTNULL="true" SEQUENCE="false"/>
      </FIELDS>
      <KEYS>
        <KEY NAME="primary" TYPE="primary" FIELDS="id"/>
        <KEY NAME="annotationid" TYPE="foreign" FIELDS="annotationid" REFTABLE="annotationsneu" REFFIELDS="id"/>
      </KEYS>
    </TABLE>
  </TABLES>
</XMLDB>
