{
	"title" : "5.2 Master Challenge 3",
	"question": "Prepare a document of a minimum of three pages explaining different types of pollution.<br><br>1. Add images wherever applicable.<br>2. Insert captions for the images.<br>3. Highlight the types of pollution.",
	"duedate": "",
	"submissionfrom": "",
	"grade_duedate": "",
	"grade":100,	
	"submission_type": "onlinefile", 
	"__submission_type_hint": "onlinetext - onlinefile - codeblock",
	"activity_instruction":"Sum of 2 numbers",	
	"submissionstatus": "yes",
	"online_text_limit":"500",
	"additional_files": "",	
	"codeblock_mode": "automate",
	"__codeblock_mode_hint": "automate - manual",
	"grade_type":"scale",
	"grading_method": "direct",
	"uid": "DCL07-TP5-CHDRN9",
	"maxfilesubmissions":"5",	
	"filetypeslist":"",	
	"maxfilesubmissions_size":"2097152",	
	"testcases" : [
	  {
		"value" : "Case = Test integer sum\ninput = 1 2 3 5\noutput = 11"
	  },
	  {
		"value" : "Case = Test integer sum\ninput = 1\n -2\n 3\n 5\noutput = 7"
	  }
	]
}