{
	"title" : "7.1 Master Challenge 3",
	"question": "Create an ArrayList of student names and their grades.<br> Students - 'John', 'Sarah', 'Tom', 'Lucy'<br>Grades - 'A', 'B', 'C', 'A'<br><br>Replace 'Tom's' grade with 'B'. Add a new student, 'Molly', with a grade 'C'. Remove 'Sarah' from the list. Print the original and updated grade lists'",
	"duedate": "",
	"submissionfrom": "",
	"grade_duedate": "",
	"grade":100,	
	"submission_type": "codeblock", 
	"__submission_type_hint": "onlinetext - onlinefile - scratch - codeblock",
	"activity_instruction":"Sum of 2 numbers",	
	"submissionstatus": "yes",
	"online_text_limit":"500",
	"additional_files": "",	
	"codeblock_mode": "manual",
	"__codeblock_mode_hint": "automate - manual",
	"language_type": "java",
	"__language_type_hint": "python - sql - htmlcss - javascript - R - pseudocode - java",
	"grade_type":"scale",
	"grading_method": "direct",
	"uid": "DPL12-TP7-CHDRN7",
	"maxfilesubmissions":"",	
	"filetypeslist":"",	
	"maxfilesubmissions_size":"",	
	"testcases" : [
	  {
		"value" : "Case = Test integer sum\ninput = 1 2 3 5\noutput = 11"
	  },
	  {
		"value" : "Case = Test integer sum\ninput = 1\n -2\n 3\n 5\noutput = 7"
	  }
	]
}