{"students":{"1558560-2711":{"username":"1558560-2711","firstname":"CHRISTIAN MAURICIO","lastname":"CACERES MERCHANCANO","num_doc":"1113691554","id_user":"90","tipo_doc":"C.C","image":"..\/..\/..\/user\/pix.php\/90\/f1.jpg"},"1558551-2711":{"username":"1558551-2711","firstname":"GIORMAN STIVEN","lastname":"RODRIGUEZ MU\u00d1OZ","num_doc":"1115087055","id_user":"87","tipo_doc":"C.C","image":"..\/..\/..\/user\/pix.php\/87\/f1.jpg"},"1554636-2712":{"username":"1554636-2712","firstname":"ALEJANDRO","lastname":"CORRALES TAFURT","num_doc":"1114898328","id_user":"85","tipo_doc":"C.C","image":"..\/..\/..\/user\/pix.php\/85\/f1.jpg"},"1531575-3140":{"username":"1531575-3140","firstname":"MIGUEL ANGEL","lastname":"GIRALDO RESTREPO","num_doc":"1116132724","id_user":"75","tipo_doc":"C.C","image":"..\/..\/..\/user\/pix.php\/75\/f1.jpg"},"1526318-3140":{"username":"1526318-3140","firstname":"MIGUEL ANGEL","lastname":"TALAGA MINA","num_doc":"1144096317","id_user":"54","tipo_doc":"C.C","image":"..\/..\/..\/user\/pix.php\/54\/f1.jpg"},"1525450-3140":{"username":"1525450-3140","firstname":"HELEN BRIGITTE","lastname":"MORENO GONZALEZ","num_doc":"98022656856","id_user":"51","tipo_doc":"T.I","image":"..\/..\/..\/user\/pix.php\/51\/f1.jpg"},"1522464-3147":{"username":"1522464-3147","firstname":"YOHAN SNEIDER","lastname":"MONTOYA RODRIGUEZ","num_doc":"1143869332","id_user":"105","tipo_doc":"C.C","image":"..\/..\/..\/user\/pix.php\/105\/f1.jpg"},"1523688-3147":{"username":"1523688-3147","firstname":"BRYAN MICHEL","lastname":"OROZCO GOMEZ","num_doc":"1116272837","id_user":"103","tipo_doc":"C.C","image":"..\/..\/..\/user\/pix.php\/103\/f1.jpg"},"1530644-3147":{"username":"1530644-3147","firstname":"JOHN ALEXANDER","lastname":"SALAZAR HERNANDEZ","num_doc":"1107511348","id_user":"73","tipo_doc":"C.C","image":"..\/..\/..\/user\/pix.php\/73\/f1.jpg"},"1529442-3147":{"username":"1529442-3147","firstname":"MATEO","lastname":"LONDO\u00d1O CASTELLANOS","num_doc":"1143872048","id_user":"68","tipo_doc":"C.C","image":"..\/..\/..\/user\/pix.php\/68\/f1.jpg"},"1526182-3147":{"username":"1526182-3147","firstname":"ADRIAN","lastname":"RIVERA LOPEZ","num_doc":"1083922004","id_user":"52","tipo_doc":"C.C","image":"..\/..\/..\/user\/pix.php\/52\/f1.jpg"},"1522792-3147":{"username":"1522792-3147","firstname":"GERMAN ANDRES","lastname":"PEREZ HURTADO","num_doc":"1107511903","id_user":"33","tipo_doc":"C.C","image":"..\/..\/..\/user\/pix.php\/33\/f1.jpg"},"1522188-3147":{"username":"1522188-3147","firstname":"JUAN MANUEL","lastname":"PADILLA HERNANDEZ","num_doc":"1144099090","id_user":"22","tipo_doc":"C.C","image":"..\/..\/..\/user\/pix.php\/22\/f1.jpg"},"1525019-3148":{"username":"1525019-3148","firstname":"DANIEL ALEJANDRO","lastname":"PE\u00d1A ESTRELLA","num_doc":"1062327389","id_user":"104","tipo_doc":"C.C","image":"..\/..\/..\/user\/pix.php\/104\/f1.jpg"},"1526969-3148":{"username":"1526969-3148","firstname":"CARLOS ALBERTO","lastname":"VALENZUELA GARZON","num_doc":"1107507952","id_user":"57","tipo_doc":"C.C","image":"..\/..\/..\/user\/pix.php\/57\/f1.jpg"},"1530344-3249":{"username":"1530344-3249","firstname":"ANGIE PAOLA","lastname":"MORENO MORENO","num_doc":"97112416092","id_user":"115","tipo_doc":"T.I","image":"..\/..\/..\/user\/pix.php\/115\/f1.jpg"},"1524513-3249":{"username":"1524513-3249","firstname":"JUAN DAVID","lastname":"RAMOS VALLEJO","num_doc":"1143983423","id_user":"99","tipo_doc":"C.C","image":"..\/..\/..\/user\/pix.php\/99\/f1.jpg"},"1530000-3249":{"username":"1530000-3249","firstname":"LINA MARSELA","lastname":"\u00d1USTES TRONCOSO","num_doc":"1144196921","id_user":"72","tipo_doc":"C.C","image":"..\/..\/..\/user\/pix.php\/72\/f1.jpg"},"1524022-3249":{"username":"1524022-3249","firstname":"YEIMY ALEJANDRA","lastname":"ARANDA CALAMBAS","num_doc":"1114489151","id_user":"46","tipo_doc":"C.C","image":"..\/..\/..\/user\/pix.php\/46\/f1.jpg"},"1526715-3250":{"username":"1526715-3250","firstname":"JOSE LUIS","lastname":"QUINTERO NARVAEZ","num_doc":"1113537729","id_user":"55","tipo_doc":"C.C","image":"..\/..\/..\/user\/pix.php\/55\/f1.jpg"},"1535578-3252":{"username":"1535578-3252","firstname":"DANIELA","lastname":"MARTINEZ YELA","num_doc":"1107514483","id_user":"83","tipo_doc":"T.I","image":"..\/..\/..\/user\/pix.php\/83\/f1.jpg"},"1523265-3252":{"username":"1523265-3252","firstname":"VICTOR MANUEL","lastname":"JIMENEZ MASMELA","num_doc":"1113685027","id_user":"39","tipo_doc":"C.C","image":"..\/..\/..\/user\/pix.php\/39\/f1.jpg"},"1522224-3252":{"username":"1522224-3252","firstname":"LEYDI MARITZA","lastname":"VALENCIA MILLAN","num_doc":"1112630711","id_user":"25","tipo_doc":"C.C","image":"..\/..\/..\/user\/pix.php\/25\/f1.jpg"},"1526787-3261":{"username":"1526787-3261","firstname":"JUAN CAMILO","lastname":"EPE NARVAEZ","num_doc":"1144094850","id_user":"56","tipo_doc":"C.C","image":"..\/..\/..\/user\/pix.php\/56\/f1.jpg"},"1533102-3263":{"username":"1533102-3263","firstname":"MANUELA","lastname":"VALENCIA MAYA","num_doc":"1144096403","id_user":"76","tipo_doc":"C.C","image":"..\/..\/..\/user\/pix.php\/76\/f1.jpg"},"1529058-3263":{"username":"1529058-3263","firstname":"LAURA JUDITH","lastname":"LOPEZ ESQUIVEL","num_doc":"1107508107","id_user":"65","tipo_doc":"C.C","image":"..\/..\/..\/user\/pix.php\/65\/f1.jpg"},"1527139-3263":{"username":"1527139-3263","firstname":"LAURA GISSEL","lastname":"MELLIZO CASTA\u00d1O","num_doc":"1144095253","id_user":"59","tipo_doc":"C.C","image":"..\/..\/..\/user\/pix.php\/59\/f1.jpg"},"1522177-3263":{"username":"1522177-3263","firstname":"BRENDA YIDITH","lastname":"MILLAN GONZALEZ","num_doc":"1144191930","id_user":"20","tipo_doc":"C.C","image":"..\/..\/..\/user\/pix.php\/20\/f1.jpg"},"1529677-3340":{"username":"1529677-3340","firstname":"MARIA ALEJANDRA","lastname":"ASCUNTAR MARTINEZ","num_doc":"1007602574","id_user":"69","tipo_doc":"C.C","image":"..\/..\/..\/user\/pix.php\/69\/f1.jpg"},"1535614-3461":{"username":"1535614-3461","firstname":"JESSICA ALEJANDRA","lastname":"RIVERA TORRES","num_doc":"1113688598","id_user":"84","tipo_doc":"C.C","image":"..\/..\/..\/user\/pix.php\/84\/f1.jpg"},"1528416-3461":{"username":"1528416-3461","firstname":"DAVID","lastname":"RAMIREZ GOMEZ","num_doc":"1143948416","id_user":"64","tipo_doc":"C.C","image":"..\/..\/..\/user\/pix.php\/64\/f1.jpg"},"1523787-3461":{"username":"1523787-3461","firstname":"LAURA ISABEL","lastname":"DE LA CRUZ OSSA","num_doc":"1116275970","id_user":"44","tipo_doc":"C.C","image":"..\/..\/..\/user\/pix.php\/44\/f1.jpg"},"1522276-3461":{"username":"1522276-3461","firstname":"NATALIA","lastname":"MORENO MU\u00d1OZ","num_doc":"1118307006","id_user":"28","tipo_doc":"C.C","image":"..\/..\/..\/user\/pix.php\/28\/f1.jpg"},"1522017-3461":{"username":"1522017-3461","firstname":"STEFANNY","lastname":"BRI\u00d1EZ GUTIERREZ","num_doc":"1234192158","id_user":"5","tipo_doc":"C.C","image":"..\/..\/..\/user\/pix.php\/5\/f1.jpg"},"1523212-3487":{"username":"1523212-3487","firstname":"MARIA ELENA","lastname":"BECERRA SEGURA","num_doc":"1113688183","id_user":"38","tipo_doc":"C.C","image":"..\/..\/..\/user\/pix.php\/38\/f1.jpg"},"1522167-3487":{"username":"1522167-3487","firstname":"VICKY YOLIMA","lastname":"LOPEZ ENRIQUEZ","num_doc":"1086332302","id_user":"17","tipo_doc":"C.C","image":"..\/..\/..\/user\/pix.php\/17\/f1.jpg"},"1522341-3545":{"username":"1522341-3545","firstname":"LEONARDO ANTONIO","lastname":"GUTIERREZ BURGOS","num_doc":"1118306796","id_user":"98","tipo_doc":"C.C","image":"..\/..\/..\/user\/pix.php\/98\/f1.jpg"},"1533618-3545":{"username":"1533618-3545","firstname":"ERIKA DANIELA","lastname":"ORTIZ JIMENEZ","num_doc":"1114063813","id_user":"77","tipo_doc":"C.C","image":"..\/..\/..\/user\/pix.php\/77\/f1.jpg"},"1529221-3545":{"username":"1529221-3545","firstname":"DANIELA","lastname":"ROBLEDO ZORRILLA","num_doc":"1144095363","id_user":"67","tipo_doc":"C.C","image":"..\/..\/..\/user\/pix.php\/67\/f1.jpg"},"1527822-3545":{"username":"1527822-3545","firstname":"JOHAN SEBASTIAN","lastname":"CHAVEZ DUQUE","num_doc":"1144198832","id_user":"62","tipo_doc":"C.C","image":"..\/..\/..\/user\/pix.php\/62\/f1.jpg"},"1522008-3545":{"username":"1522008-3545","firstname":"LAURA","lastname":"AVILA RODRIGUEZ","num_doc":"1144100096","id_user":"4","tipo_doc":"C.C","image":"..\/..\/..\/user\/pix.php\/4\/f1.jpg"},"1522165-3550":{"username":"1522165-3550","firstname":"BRENDA GISELA","lastname":"JARAMILLO PEREZ","num_doc":"1113685957","id_user":"16","tipo_doc":"C.C","image":"..\/..\/..\/user\/pix.php\/16\/f1.jpg"},"1535525-3551":{"username":"1535525-3551","firstname":"LINA FERNANDA","lastname":"ZAPATA ORDO\u00d1EZ","num_doc":"1113686853","id_user":"82","tipo_doc":"C.C","image":"..\/..\/..\/user\/pix.php\/82\/f1.jpg"},"1535641-3646":{"username":"1535641-3646","firstname":"JESSICA LORENA","lastname":"DELGADO ERAZO","num_doc":"1144094663","id_user":"109","tipo_doc":"C.C","image":"..\/..\/..\/user\/pix.php\/109\/f1.jpg"},"1527623-3647":{"username":"1527623-3647","firstname":"ALEJANDRA","lastname":"SANDOVAL VILLARREAL","num_doc":"1144204894","id_user":"116","tipo_doc":"C.C","image":"..\/..\/..\/user\/pix.php\/116\/f1.jpg"},"1535189-3660":{"username":"1535189-3660","firstname":"LEYDY JOHANA","lastname":"AZA ORDO\u00d1EZ","num_doc":"1089480928","id_user":"80","tipo_doc":"C.C","image":"..\/..\/..\/user\/pix.php\/80\/f1.jpg"},"1524616-3660":{"username":"1524616-3660","firstname":"ANGIE MELISSA","lastname":"ERASO RIVERA","num_doc":"1144101341","id_user":"47","tipo_doc":"C.C","image":"..\/..\/..\/user\/pix.php\/47\/f1.jpg"},"1523052-3660":{"username":"1523052-3660","firstname":"JEFREY","lastname":"MARTINEZ OSPINA","num_doc":"1113684885","id_user":"37","tipo_doc":"C.C","image":"..\/..\/..\/user\/pix.php\/37\/f1.jpg"},"1522989-3660":{"username":"1522989-3660","firstname":"LUISA MARIA","lastname":"SALAS MARIN","num_doc":"99041211195","id_user":"36","tipo_doc":"T.I","image":"..\/..\/..\/user\/pix.php\/36\/f1.jpg"},"1522083-3660":{"username":"1522083-3660","firstname":"VALERIA","lastname":"MURIEL BEJARANO","num_doc":"1113690469","id_user":"10","tipo_doc":"C.C","image":"..\/..\/..\/user\/pix.php\/10\/f1.jpg"},"1527991-3740":{"username":"1527991-3740","firstname":"SANTIAGO","lastname":"RODAS ARIAS","num_doc":"98111218501","id_user":"63","tipo_doc":"T.I","image":"..\/..\/..\/user\/pix.php\/63\/f1.jpg"},"1527626-3740":{"username":"1527626-3740","firstname":"CRISTIAN DAVID","lastname":"URBANO ROJAS","num_doc":"1089348811","id_user":"61","tipo_doc":"C.C","image":"..\/..\/..\/user\/pix.php\/61\/f1.jpg"},"1524905-3740":{"username":"1524905-3740","firstname":"NATALIA","lastname":"LEMOS GARCIA","num_doc":"1107513735","id_user":"49","tipo_doc":"C.C","image":"..\/..\/..\/user\/pix.php\/49\/f1.jpg"},"1522195-3740":{"username":"1522195-3740","firstname":"SANTIAGO ERNESTO","lastname":"PRADO PANTOJA","num_doc":"1086500201","id_user":"24","tipo_doc":"C.C","image":"..\/..\/..\/user\/pix.php\/24\/f1.jpg"},"1522088-3741":{"username":"1522088-3741","firstname":"JOSE DAVID","lastname":"OROZCO CONDE","num_doc":"1144200248","id_user":"101","tipo_doc":"C.C","image":"..\/..\/..\/user\/pix.php\/101\/f1.jpg"},"1522179-3741":{"username":"1522179-3741","firstname":"JOSE LUIS","lastname":"MONTOYA ZAMBRANO","num_doc":"1113687058","id_user":"21","tipo_doc":"C.C","image":"..\/..\/..\/user\/pix.php\/21\/f1.jpg"},"1535038-3743":{"username":"1535038-3743","firstname":"CARLOS FELIPE","lastname":"MONTOYA RINCON","num_doc":"1144099302","id_user":"78","tipo_doc":"C.C","image":"..\/..\/..\/user\/pix.php\/78\/f1.jpg"},"1529933-3743":{"username":"1529933-3743","firstname":"NESTOR ALBERTO","lastname":"CARDONA CAMPO","num_doc":"1144178314","id_user":"71","tipo_doc":"C.C","image":"..\/..\/..\/user\/pix.php\/71\/f1.jpg"},"1523548-3743":{"username":"1523548-3743","firstname":"IVAN MAURICIO","lastname":"TORO CIFUENTES","num_doc":"1010059777","id_user":"42","tipo_doc":"C.C","image":"..\/..\/..\/user\/pix.php\/42\/f1.jpg"},"1522175-3743":{"username":"1522175-3743","firstname":"DAVID","lastname":"MERA GALLO","num_doc":"1107512854","id_user":"19","tipo_doc":"C.C","image":"..\/..\/..\/user\/pix.php\/19\/f1.jpg"},"1526982-3744":{"username":"1526982-3744","firstname":"JAIMEN JUNIOR","lastname":"AZA TAIMAL","num_doc":"1088597617","id_user":"58","tipo_doc":"C.C","image":"..\/..\/..\/user\/pix.php\/58\/f1.jpg"},"1523982-3744":{"username":"1523982-3744","firstname":"JOSE DAVID","lastname":"LIBREROS MU\u00d1OZ","num_doc":"1144095243","id_user":"45","tipo_doc":"C.C","image":"..\/..\/..\/user\/pix.php\/45\/f1.jpg"},"1522897-3744":{"username":"1522897-3744","firstname":"MARIO ESTEBAN","lastname":"ESTRADA GONZALEZ","num_doc":"98061860460","id_user":"34","tipo_doc":"T.I","image":"..\/..\/..\/user\/pix.php\/34\/f1.jpg"},"1522317-3744":{"username":"1522317-3744","firstname":"CRISTIAN ALIRIO","lastname":"\u00d1A\u00d1EZ DAVILA","num_doc":"1088976099","id_user":"29","tipo_doc":"C.C","image":"..\/..\/..\/user\/pix.php\/29\/f1.jpg"},"1522158-3744":{"username":"1522158-3744","firstname":"EYMER DANIEL","lastname":"GUAQUEZ DOMINGUEZ","num_doc":"1006034057","id_user":"14","tipo_doc":"C.C","image":"..\/..\/..\/user\/pix.php\/14\/f1.jpg"},"1522142-3745":{"username":"1522142-3745","firstname":"CARLOS ALBERTO","lastname":"CADENA PILLIMUE","num_doc":"98011363687","id_user":"110","tipo_doc":"T.I","image":"..\/..\/..\/user\/pix.php\/110\/f1.jpg"},"1522052-3745":{"username":"1522052-3745","firstname":"JUAN CAMILO","lastname":"HENAO BERMUDEZ","num_doc":"98102306821","id_user":"8","tipo_doc":"T.I","image":"..\/..\/..\/user\/pix.php\/8\/f1.jpg"},"1535219-3746":{"username":"1535219-3746","firstname":"CRISTIAN JUAN CARLOS","lastname":"MELO GRIJALBA","num_doc":"1087048504","id_user":"81","tipo_doc":"C.C","image":"..\/..\/..\/user\/pix.php\/81\/f1.jpg"},"1522259-3746":{"username":"1522259-3746","firstname":"TITO FAUSTO","lastname":"FAJARDO RODRIGUEZ","num_doc":"1087205805","id_user":"27","tipo_doc":"C.C","image":"..\/..\/..\/user\/pix.php\/27\/f1.jpg"},"1522189-3746":{"username":"1522189-3746","firstname":"HAROLD CAMILO","lastname":"PALACIOS BASTIDAS","num_doc":"1118308111","id_user":"23","tipo_doc":"C.C","image":"..\/..\/..\/user\/pix.php\/23\/f1.jpg"},"1522040-3746":{"username":"1522040-3746","firstname":"DANIEL FELIPE","lastname":"FAJARDO ESPINOSA","num_doc":"1086139758","id_user":"6","tipo_doc":"C.C","image":"..\/..\/..\/user\/pix.php\/6\/f1.jpg"},"1522006-3746":{"username":"1522006-3746","firstname":"GUSTAVO ADOLFO","lastname":"ARTEAGA ESTACIO","num_doc":"1144097955","id_user":"3","tipo_doc":"C.C","image":"..\/..\/..\/user\/pix.php\/3\/f1.jpg"},"1625568-3747":{"username":"1625568-3747","firstname":"KATERIN VIVIANA","lastname":"MU\u00d1OZ LEITON","num_doc":"1004711380","id_user":"96","tipo_doc":"C.C","image":"..\/..\/..\/user\/pix.php\/96\/f1.jpg"},"1529748-3747":{"username":"1529748-3747","firstname":"MICHAEL STEVEN","lastname":"CERON MALES","num_doc":"1087424383","id_user":"70","tipo_doc":"C.C","image":"..\/..\/..\/user\/pix.php\/70\/f1.jpg"},"1525225-3747":{"username":"1525225-3747","firstname":"CRISTHIAN FERNANDO","lastname":"ORTEGA BURBANO","num_doc":"1085663329","id_user":"50","tipo_doc":"C.C","image":"..\/..\/..\/user\/pix.php\/50\/f1.jpg"},"1524703-3747":{"username":"1524703-3747","firstname":"JENNY LIZBETH","lastname":"TAIMAL AZA","num_doc":"1144100937","id_user":"48","tipo_doc":"C.C","image":"..\/..\/..\/user\/pix.php\/48\/f1.jpg"},"1522923-3747":{"username":"1522923-3747","firstname":"JUAN DAVID","lastname":"ROJAS ESQUIVEL","num_doc":"1144100473","id_user":"35","tipo_doc":"C.C","image":"..\/..\/..\/user\/pix.php\/35\/f1.jpg"},"1522101-3747":{"username":"1522101-3747","firstname":"JEYSSON STIVEN","lastname":"PORTILLO MELO","num_doc":"1144100784","id_user":"11","tipo_doc":"C.C","image":"..\/..\/..\/user\/pix.php\/11\/f1.jpg"},"1522842-3748":{"username":"1522842-3748","firstname":"LEON FELIPE","lastname":"GONZALEZ MEDINA","num_doc":"1144101928","id_user":"114","tipo_doc":"C.C","image":"..\/..\/..\/user\/pix.php\/114\/f1.jpg"},"1522239-3748":{"username":"1522239-3748","firstname":"PABLO SEBASTIAN","lastname":"BENAVIDES PALACIOS","num_doc":"1144095648","id_user":"112","tipo_doc":"C.C","image":"..\/..\/..\/user\/pix.php\/112\/f1.jpg"},"1523956-3748":{"username":"1523956-3748","firstname":"CRISTIAN EDUARDO","lastname":"MU\u00d1OZ CASTA\u00d1EDA","num_doc":"1118307439","id_user":"102","tipo_doc":"C.C","image":"..\/..\/..\/user\/pix.php\/102\/f1.jpg"},"1531360-3748":{"username":"1531360-3748","firstname":"JAIME ALEXANDER","lastname":"SIERRA MONTA\u00d1O","num_doc":"1144058484","id_user":"74","tipo_doc":"C.C","image":"..\/..\/..\/user\/pix.php\/74\/f1.jpg"},"1526215-3748":{"username":"1526215-3748","firstname":"JAIME ANDRES","lastname":"MU\u00d1OZ HOYOS","num_doc":"1088975893","id_user":"53","tipo_doc":"C.C","image":"..\/..\/..\/user\/pix.php\/53\/f1.jpg"},"1523320-3748":{"username":"1523320-3748","firstname":"IAN NICOLAS","lastname":"CHIVATA RODRIGUEZ","num_doc":"1113686588","id_user":"40","tipo_doc":"C.C","image":"..\/..\/..\/user\/pix.php\/40\/f1.jpg"},"1522434-3748":{"username":"1522434-3748","firstname":"FAIVER DUVAN","lastname":"MANQUILLO LOPEZ","num_doc":"1144094550","id_user":"31","tipo_doc":"C.C","image":"..\/..\/..\/user\/pix.php\/31\/f1.jpg"},"1522160-3748":{"username":"1522160-3748","firstname":"BRAYAN MANUEL","lastname":"GUERRERO MARTINEZ","num_doc":"1144101510","id_user":"15","tipo_doc":"C.C","image":"..\/..\/..\/user\/pix.php\/15\/f1.jpg"},"1624955-3749":{"username":"1624955-3749","firstname":"JHON JAIRO","lastname":"FAJARDO CALVACHE","num_doc":"1085335743","id_user":"95","tipo_doc":"C.C","image":"..\/..\/..\/user\/pix.php\/95\/f1.jpg"},"1535120-3749":{"username":"1535120-3749","firstname":"JUAN DAVID","lastname":"URREA ACEVEDO","num_doc":"1107512951","id_user":"79","tipo_doc":"C.C","image":"..\/..\/..\/user\/pix.php\/79\/f1.jpg"},"1523576-3749":{"username":"1523576-3749","firstname":"JULIANA","lastname":"VILLARRUEL CIFUENTES","num_doc":"98092853250","id_user":"43","tipo_doc":"T.I","image":"..\/..\/..\/user\/pix.php\/43\/f1.jpg"},"1523539-3749":{"username":"1523539-3749","firstname":"NATALIA","lastname":"MONTOYA MARIN","num_doc":"1113792010","id_user":"41","tipo_doc":"C.C","image":"..\/..\/..\/user\/pix.php\/41\/f1.jpg"},"1522720-3749":{"username":"1522720-3749","firstname":"LINA MARCELA","lastname":"ROSERO ORDO\u00d1EZ","num_doc":"1144098511","id_user":"32","tipo_doc":"C.C","image":"..\/..\/..\/user\/pix.php\/32\/f1.jpg"},"1522169-3749":{"username":"1522169-3749","firstname":"MANUEL SANTIAGO","lastname":"MOCONDINO ERASO","num_doc":"1085948064","id_user":"18","tipo_doc":"C.C","image":"..\/..\/..\/user\/pix.php\/18\/f1.jpg"},"1522049-3749":{"username":"1522049-3749","firstname":"NICOLAS FELIPE","lastname":"GONZALEZ IPIA","num_doc":"1144096574","id_user":"7","tipo_doc":"C.C","image":"..\/..\/..\/user\/pix.php\/7\/f1.jpg"},"1558559-3751":{"username":"1558559-3751","firstname":"PAOLA ANDREA","lastname":"PINILLA GAVIRIA","num_doc":"1116275427","id_user":"118","tipo_doc":"C.C","image":"..\/..\/..\/user\/pix.php\/118\/f1.jpg"},"1550001-3751":{"username":"1550001-3751","firstname":"KEVIN STIVEN","lastname":"BOLIVAR GUZMAN","num_doc":"1115089324","id_user":"113","tipo_doc":"C.C","image":"..\/..\/..\/user\/pix.php\/113\/f1.jpg"},"1558624-3751":{"username":"1558624-3751","firstname":"LIZETH VALERIA","lastname":"RIASCOS RAMIREZ","num_doc":"1113690658","id_user":"94","tipo_doc":"C.C","image":"..\/..\/..\/user\/pix.php\/94\/f1.jpg"},"1558553-3751":{"username":"1558553-3751","firstname":"JHON EDINSON","lastname":"VALENCIA ALBORNOZ","num_doc":"1115088622","id_user":"89","tipo_doc":"C.C","image":"..\/..\/..\/user\/pix.php\/89\/f1.jpg"},"1558552-3751":{"username":"1558552-3751","firstname":"INES MARINA","lastname":"ROLDAN LUQUE","num_doc":"1115089635","id_user":"88","tipo_doc":"C.C","image":"..\/..\/..\/user\/pix.php\/88\/f1.jpg"},"1558550-3751":{"username":"1558550-3751","firstname":"ANGIE DANIELA","lastname":"PEREA RIOS","num_doc":"1116276049","id_user":"86","tipo_doc":"C.C","image":"..\/..\/..\/user\/pix.php\/86\/f1.jpg"},"1522253-3751":{"username":"1522253-3751","firstname":"LUIS DANIEL","lastname":"DIAZ TAPIA","num_doc":"1089245129","id_user":"26","tipo_doc":"C.C","image":"..\/..\/..\/user\/pix.php\/26\/f1.jpg"},"1522116-3751":{"username":"1522116-3751","firstname":"ANDRES FELIPE","lastname":"SOLARTE","num_doc":"1112490039","id_user":"13","tipo_doc":"C.C","image":"..\/..\/..\/user\/pix.php\/13\/f1.jpg"},"1531110-3753":{"username":"1531110-3753","firstname":"JOAQUIN FELIPE","lastname":"GALLEGO PUERTO","num_doc":"1118237133","id_user":"108","tipo_doc":"C.C","image":"..\/..\/..\/user\/pix.php\/108\/f1.jpg"},"1526713-3753":{"username":"1526713-3753","firstname":"ERICKA MELISSA","lastname":"VILLOTA MAYA","num_doc":"1144065936","id_user":"107","tipo_doc":"C.C","image":"..\/..\/..\/user\/pix.php\/107\/f1.jpg"},"1522023-3753":{"username":"1522023-3753","firstname":"ANGELA MILDRETH","lastname":"CASTRO PI\u00d1ACUE","num_doc":"1144201550","id_user":"106","tipo_doc":"C.C","image":"..\/..\/..\/user\/pix.php\/106\/f1.jpg"},"1535513-3753":{"username":"1535513-3753","firstname":"ANGELA GABRIELA","lastname":"YAMA JARAMILLO","num_doc":"1004550523","id_user":"97","tipo_doc":"C.C","image":"..\/..\/..\/user\/pix.php\/97\/f1.jpg"},"1522059-3754":{"username":"1522059-3754","firstname":"EVELYN CRISTINA","lastname":"JIMENEZ ROSERO","num_doc":"1085339336","id_user":"111","tipo_doc":"C.C","image":"..\/..\/..\/user\/pix.php\/111\/f1.jpg"},"1522451-3754":{"username":"1522451-3754","firstname":"SEBASTIAN","lastname":"BORRERO GARCIA","num_doc":"1107509167","id_user":"100","tipo_doc":"C.C","image":"..\/..\/..\/user\/pix.php\/100\/f1.jpg"},"1522371-3754":{"username":"1522371-3754","firstname":"INGRID TATIANA","lastname":"URBANO GOMEZ","num_doc":"1004631230","id_user":"30","tipo_doc":"C.C","image":"..\/..\/..\/user\/pix.php\/30\/f1.jpg"},"1522115-3754":{"username":"1522115-3754","firstname":"KAREN JULIANA","lastname":"SILVA PINTO","num_doc":"1081733324","id_user":"12","tipo_doc":"C.C","image":"..\/..\/..\/user\/pix.php\/12\/f1.jpg"},"1522061-3754":{"username":"1522061-3754","firstname":"JUAN DAVID","lastname":"JOJOA ORTIZ","num_doc":"98081361185","id_user":"9","tipo_doc":"T.I","image":"..\/..\/..\/user\/pix.php\/9\/f1.jpg"},"1558622-3841":{"username":"1558622-3841","firstname":"PAOLA ANDREA","lastname":"MINA NEIVA","num_doc":"99020110232","id_user":"93","tipo_doc":"T.I","image":"..\/..\/..\/user\/pix.php\/93\/f1.jpg"},"1558621-3841":{"username":"1558621-3841","firstname":"LUISA FERNANDA","lastname":"ARIAS DIAZ","num_doc":"1111813129","id_user":"92","tipo_doc":"C.C","image":"..\/..\/..\/user\/pix.php\/92\/f1.jpg"},"1558619-3841":{"username":"1558619-3841","firstname":"ALEX ANTONY","lastname":"VIERA CARDONA","num_doc":"1111812547","id_user":"91","tipo_doc":"C.C","image":"..\/..\/..\/user\/pix.php\/91\/f1.jpg"},"1527433-3841":{"username":"1527433-3841","firstname":"YESICA NATALIA","lastname":"MU\u00d1OZ BRAVO","num_doc":"1234189928","id_user":"60","tipo_doc":"C.C","image":"..\/..\/..\/user\/pix.php\/60\/f1.jpg"},"1529421-3845":{"username":"1529421-3845","firstname":"OLMER ALEJANDRO","lastname":"MU\u00d1OZ CORDOBA","num_doc":"1059354679","id_user":"117","tipo_doc":"C.C","image":"..\/..\/..\/user\/pix.php\/117\/f1.jpg"},"1529136-3845":{"username":"1529136-3845","firstname":"JHON ALEXIS","lastname":"VALENCIA MENESES","num_doc":"1143852514","id_user":"66","tipo_doc":"C.C","image":"..\/..\/..\/user\/pix.php\/66\/f1.jpg"}}}