{"name":"LearnerScript","description":"Demo of Learner Script Plugin","pathmatch":"\/blocks\/reportdashboard\/dashboard.php","enabled":"1","sortorder":"3","configdata":"{\"placement\":\"top\",\"orphan\":\"0\",\"backdrop\":\"0\",\"reflex\":\"0\",\"filtervalues\":{\"role\":[],\"theme\":[]},\"majorupdatetime\":1520828405}","version":"2017051500","steps":[{"title":"Welcome","content":"Welcome to Learner Script an efficient reporting engine for Moodle.","targettype":"2","targetvalue":"","sortorder":"0","configdata":"{}"},{"title":"Switch Dashboard","content":"Click here to switch from one dashboard to another dashboard.","targettype":"0","targetvalue":"#switchdashboard","sortorder":"1","configdata":"{}"},{"title":"Add Widgets\/Tiles","content":"Click here to add a new widget\/tile to dashboard.","targettype":"0","targetvalue":"#addwidgets","sortorder":"2","configdata":"{}"},{"title":"Add New Report","content":"Click here to add new report.","targettype":"0","targetvalue":"#addreport","sortorder":"3","configdata":"{}"},{"title":"Add New Dashboard","content":"Click here to add new dashboard.","targettype":"0","targetvalue":"#adddashboard","sortorder":"4","configdata":"{}"},{"title":"Switch Role","content":"Click here to see the report or Dashboard according to the user role.","targettype":"0","targetvalue":"#switchrole","sortorder":"5","configdata":"{}"},{"title":"Date Filter","content":"Select your custom filter to filter the dashboard or a report according to week, month, year, custom and all.","targettype":"0","targetvalue":"#reportbox_shadow","sortorder":"6","configdata":"{}"},{"title":"Export Report","content":"Click here to export the report.","targettype":"0","targetvalue":"#exportoptions","sortorder":"7","configdata":"{}"}]}